dwdwfsapi/__init__.py
dwdwfsapi/core.py
dwdwfsapi/weatherwarnings.py
dwdwfsapi-1.0.8.dist-info/METADATA
dwdwfsapi-1.0.8.dist-info/WHEEL
dwdwfsapi-1.0.8.dist-info/licenses/LICENSE
dwdwfsapi-1.0.8.dist-info/RECORD
