Metadata-Version: 2.1
Name: dwdwfsapi
Version: 1.0.8
Summary: Python client to retrieve data provided by DWD via their geoserver WFS API
Project-URL: Homepage, https://github.com/stephan192/dwdwfsapi
Project-URL: Issues, https://github.com/stephan192/dwdwfsapi/issues
Author-email: stephan192 <stephan192@outlook.com>
License-File: LICENSE
Keywords: deutscher wetterdienst,dwd,ows,wfs
Classifier: Development Status :: 5 - Production/Stable
Classifier: License :: OSI Approved :: MIT License
Classifier: Operating System :: OS Independent
Classifier: Programming Language :: Python :: 3
Requires-Python: >=3.11
Requires-Dist: requests>=2.31.0
Requires-Dist: urllib3>=1.26.5
